gwc_viacom/__init__.py
gwc_viacom-0.1.dist-info/DESCRIPTION.rst
gwc_viacom-0.1.dist-info/METADATA
gwc_viacom-0.1.dist-info/RECORD
gwc_viacom-0.1.dist-info/WHEEL
gwc_viacom-0.1.dist-info/metadata.json
gwc_viacom-0.1.dist-info/top_level.txt
