Metadata-Version: 2.0
Name: gwc-viacom
Version: 0.1
Summary: GWC Viacom 2016 Principles of Coding
Home-page: http://github.com/kathrynthegreat/gwc_viacom
Author: GWC Viacom 2016
Author-email: kvasilaky@gmail.com
License: GWC
Platform: UNKNOWN
